{
  "title": "Vi-like shhortcuts = Option +h,j,k,l = left,down, up, right; Option+Ctrl+h,j,k,l = Ctrl+left,down,up,right",
  "rules": [
    {
      "description": "Vi Mode [left_option + hjkl]",
      "manipulators": [
        {
          "from": {
            "key_code": "h",
            "modifiers": {
              "mandatory": [
                "option"
              ],
              "optional": [
                "any"
              ]
            }
          },
          "to": [
            {
              "key_code": "left_arrow"
            }
          ],
          "type": "basic"
        },
        {
          "from": {
            "key_code": "j",
            "modifiers": {
              "mandatory": [
                "option"
              ],
              "optional": [
                "any"
              ]
            }
          },
          "to": [
            {
              "key_code": "down_arrow"
            }
          ],
          "type": "basic"
        },
        {
          "from": {
            "key_code": "k",
            "modifiers": {
              "mandatory": [
                "option"
              ],
              "optional": [
                "any"
              ]
            }
          },
          "to": [
            {
              "key_code": "up_arrow"
            }
          ],
          "type": "basic"
        },
        {
          "from": {
            "key_code": "l",
            "modifiers": {
              "mandatory": [
                "option"
              ],
              "optional": [
                "any"
              ]
            }
          },
          "to": [
            {
              "key_code": "right_arrow"
            }
          ],
          "type": "basic"
        }
      ]
    }
  ]
}
